sklearn2c/__init__.py
sklearn2c/generic_exporter.py
sklearn2c/classifiers/__init__.py
sklearn2c/classifiers/base_classifier.py
sklearn2c/classifiers/bayes.py
sklearn2c/classifiers/clf_exporter.py
sklearn2c/classifiers/dtc.py
sklearn2c/classifiers/knn.py
sklearn2c/classifiers/svc.py
sklearn2c/clustering/__init__.py
sklearn2c/clustering/base_clustering.py
sklearn2c/clustering/clus_exporter.py
sklearn2c/clustering/dbscan.py
sklearn2c/clustering/dbscan_book.py
sklearn2c/clustering/kmeans.py
sklearn2c/regressors/__init__.py
sklearn2c/regressors/base_regressor.py
sklearn2c/regressors/dtr.py
sklearn2c/regressors/knn.py
sklearn2c/regressors/linear_reg.py
sklearn2c/regressors/polynomial_reg.py
sklearn2c/regressors/reg_exporter.py
sklearn2c-0.0.4.dist-info/LICENSE
sklearn2c-0.0.4.dist-info/METADATA
sklearn2c-0.0.4.dist-info/WHEEL
sklearn2c-0.0.4.dist-info/entry_points.txt
sklearn2c-0.0.4.dist-info/top_level.txt
sklearn2c-0.0.4.dist-info/RECORD
