Metadata-Version: 2.1
Name: sklearn2c
Version: 0.0.4
Summary: A simple tool to embed scikit-learn models into microcontrollers
Maintainer-email: EmbeddedML <berkanh@gmail.com>
License: MIT License
Project-URL: Homepage, https://github.com/EmbeddedML/sklearn2c
Project-URL: Issue Tracker, https://github.com/EmbeddedML/sklearn2c/issues/
Keywords: embedded,machine learning,scikit-learn
Classifier: License :: OSI Approved :: MIT License
Classifier: Programming Language :: Python
Classifier: Programming Language :: Python :: 3
Requires-Python: >=3.6
License-File: LICENSE
Requires-Dist: scikit-learn
Requires-Dist: numpy
